mlnotify/__init__.py
mlnotify/hooks.py
mlnotify/jupyter_magic.py
mlnotify/logger.py
mlnotify/mlnotify.py
mlnotify/plugin_manager.py
mlnotify/plugins/__init__.py
mlnotify/plugins/base.py
mlnotify/plugins/notify.py
mlnotify/py.typed
mlnotify-1.0.51.dist-info/LICENSE
mlnotify-1.0.51.dist-info/WHEEL
mlnotify-1.0.51.dist-info/METADATA
mlnotify-1.0.51.dist-info/RECORD
